ncaadb/__init__.py
ncaadb/const.py
ncaadb/file.py
ncaadb/hex.py
ncaadb/read.py
ncaadb-0.1.1.dist-info/LICENSE
ncaadb-0.1.1.dist-info/METADATA
ncaadb-0.1.1.dist-info/WHEEL
ncaadb-0.1.1.dist-info/RECORD
