Metadata-Version: 2.1
Name: ncaadb
Version: 0.1.1
Summary: Handle DB save files from EA Sports NCAA games
License: GNU General Public License v3.0
Author: Hans Missenheim
Author-email: hansmissenheim@gmail.com
Requires-Python: >=3.11,<4.0
Classifier: License :: Other/Proprietary License
Classifier: Programming Language :: Python :: 3
Classifier: Programming Language :: Python :: 3.11
Classifier: Programming Language :: Python :: 3.12
Requires-Dist: pandas (>=2.0.2,<3.0.0)
